MultiServiciosWeb/__init__.py
MultiServiciosWeb/valida_curp.py
multiserviciosweb-1.1.1.dist-info/licenses/LICENSE
multiserviciosweb-1.1.1.dist-info/METADATA
multiserviciosweb-1.1.1.dist-info/WHEEL
multiserviciosweb-1.1.1.dist-info/top_level.txt
multiserviciosweb-1.1.1.dist-info/RECORD
