Metadata-Version: 2.4
Name: multiserviciosweb
Version: 1.1.1
Summary: Validate, calculate and obtain CURP information in México.
Home-page: https://github.com/EdsonBurgosMsWeb/valida-curp-client-py
Author: Edson Burgos
Author-email: Edson Burgos <edsonburgosmacedo@gmail.com>
License: MIT
Project-URL: Homepage, https://valida-curp.com.mx/
Project-URL: Repository, https://github.com/EdsonBurgosMsWeb/valida-curp-client-py
Project-URL: Bug Reports, https://github.com/EdsonBurgosMsWeb/valida-curp-client-py/issues
Project-URL: Documentation, https://api.valida-curp.com.mx/documentacion/
Keywords: valida,curp,méxico,client,api
Classifier: Development Status :: 5 - Production/Stable
Classifier: Intended Audience :: Developers
Classifier: License :: OSI Approved :: MIT License
Classifier: Operating System :: OS Independent
Classifier: Programming Language :: Python :: 3
Classifier: Programming Language :: Python :: 3.7
Classifier: Programming Language :: Python :: 3.8
Classifier: Programming Language :: Python :: 3.9
Classifier: Programming Language :: Python :: 3.10
Classifier: Programming Language :: Python :: 3.11
Classifier: Programming Language :: Python :: 3.12
Classifier: Topic :: Software Development :: Libraries :: Python Modules
Classifier: Topic :: Internet :: WWW/HTTP :: Dynamic Content
Requires-Python: >=3.7
License-File: LICENSE
Requires-Dist: requests>=2.25.0
Requires-Dist: python-dotenv>=0.19.0
Provides-Extra: dev
Requires-Dist: pytest>=6.0; extra == "dev"
Requires-Dist: pytest-cov>=2.0; extra == "dev"
Requires-Dist: black>=21.0; extra == "dev"
Requires-Dist: flake8>=3.8; extra == "dev"
Requires-Dist: mypy>=0.800; extra == "dev"
Dynamic: author
Dynamic: home-page
Dynamic: license-file
Dynamic: requires-python
